[
  {
    "perfIx": 67371,
    "movie": "Portrait of a Lady on Fire",
    "venue": "Cinema.com.hk",
    "date": "2026-03-30",
    "time": "11:30",
    "total": 94,
    "available": 39,
    "blocked": 0,
    "sold": 55,
    "gross": 7150,
    "price": 130,
    "last_updated": "2026-03-24 06:26:31 PM IST"
  },
  {
    "perfIx": 70016,
    "movie": "The Worst Person In The World",
    "venue": "Cinema.com.hk",
    "date": "2026-03-30",
    "time": "11:20",
    "total": 119,
    "available": 99,
    "blocked": 0,
    "sold": 20,
    "gross": 1900,
    "price": 95,
    "last_updated": "2026-03-24 06:26:31 PM IST"
  },
  {
    "perfIx": 70899,
    "movie": "ENHYPEN [WALK THE LINE SUMMER EDITION] IN CINEMAS (2026)",
    "venue": "Cinema.com.hk",
    "date": "2026-03-30",
    "time": "11:20",
    "total": 81,
    "available": 72,
    "blocked": 0,
    "sold": 9,
    "gross": 1170,
    "price": 130,
    "last_updated": "2026-03-24 06:26:31 PM IST"
  },
  {
    "perfIx": 73118,
    "movie": "AOT: THE LAST ATTACK Eren\u2019s Birthday Screening",
    "venue": "Cinema.com.hk",
    "date": "2026-03-30",
    "time": "11:00",
    "total": 156,
    "available": 85,
    "blocked": 0,
    "sold": 71,
    "gross": 12425,
    "price": 175,
    "last_updated": "2026-03-24 06:26:31 PM IST"
  },
  {
    "perfIx": 73133,
    "movie": "Kill Bill: The Whole Bloody Affair",
    "venue": "Cinema.com.hk",
    "date": "2026-03-30",
    "time": "06:30",
    "total": 144,
    "available": 142,
    "blocked": 0,
    "sold": 2,
    "gross": 440,
    "price": 220,
    "last_updated": "2026-03-24 06:26:31 PM IST"
  },
  {
    "perfIx": 73134,
    "movie": "Kill Bill: The Whole Bloody Affair",
    "venue": "Cinema.com.hk",
    "date": "2026-03-30",
    "time": "11:20",
    "total": 144,
    "available": 144,
    "blocked": 0,
    "sold": 0,
    "gross": 0,
    "price": 220,
    "last_updated": "2026-03-24 06:26:31 PM IST"
  }
]