[
  {
    "perfIx": 63511,
    "movie": "Two to One(GFF 2026)",
    "venue": "Cinema.com.hk",
    "date": "2026-04-29",
    "time": "11:40",
    "total": 119,
    "available": 102,
    "blocked": 0,
    "sold": 17,
    "gross": 1615,
    "price": 95,
    "last_updated": "2026-03-25 09:32:26 AM IST"
  },
  {
    "perfIx": 73126,
    "movie": "Power To The People: John & Yoko Live in NYC (2026)",
    "venue": "Cinema.com.hk",
    "date": "2026-04-29",
    "time": "12:00",
    "total": 144,
    "available": 138,
    "blocked": 0,
    "sold": 6,
    "gross": 780,
    "price": 130,
    "last_updated": "2026-03-25 09:32:26 AM IST"
  }
]